setup.py
src/cashflow/README.txt
src/cashflow/__init__.py
src/cashflow/analyze.py
src/cashflow/book.py
src/cashflow/command.py
src/cashflow/format.py
src/cashflow/oxm.py
src/cashflow/reports.py
src/cashflow/sample.gnucash
src/cashflow/tests.py
src/cashflow.egg-info/PKG-INFO
src/cashflow.egg-info/SOURCES.txt
src/cashflow.egg-info/dependency_links.txt
src/cashflow.egg-info/entry_points.txt
src/cashflow.egg-info/top_level.txt