Metadata-Version: 1.0
Name: cashflow
Version: 1.0
Summary: Reads a Gnucash file and computes your cash flow
Home-page: UNKNOWN
Author: Brandon Craig Rhodes
Author-email: brandon@rhodesmill.org
License: GPL
Platform: UNKNOWN
Classifier: License :: OSI Approved :: GNU General Public License (GPL)
Classifier: Intended Audience :: End Users/Desktop
Classifier: Intended Audience :: Financial and Insurance Industry
Classifier: Environment :: Console
Classifier: Development Status :: 5 - Production/Stable
Classifier: Operating System :: OS Independent
Classifier: Topic :: Office/Business
Classifier: Topic :: Office/Business :: Financial
Classifier: Topic :: Office/Business :: Financial :: Accounting
